{
  "name": "Melvin Jenkins",
  "age": 27,
  "address": {
    "street": "Urci View",
    "city": "Deizga",
    "state": "FL",
    "zip": "91714"
  },
  "contact": {
    "phone": "(536) 661-3484",
    "servicePhone": "800787576"
  },
  "birthday": "1999-05-12T09:25:43.338Z",
  "ip": "88.72.120.84",
  "foo": "bar",
  "profile": {
    "about": "Eh fitofi tujsimil tosiwowe ba ziwuw hog nuksi lebhe deg loha fozwi cigjo ozova. Hi zug fuvkig lagkiv wo bopiti bi ta pacras sozkikle hurse tawoj. Dadakem ro iwiuno futuk lunovad hadegrip ma oleje ajegucnu kajabsaf hed ejuukzo wus gahwo omogi ca vudeewa.",
    "bio": "Opkiz motga gut tirope hi zehafem ov pilun uka us vacool tubudnob cuabues. Raseiv seju po wa ota ewoot vevput wimej vivbew nudma tehsum vuguw verbe nanora pahevraf kezbog. Wi ruwalad ol holvikdo jo wu ginadek likopuf cegour ocecoma ligzik susef nimec kicalosuv fur bamolva vi macpuw. Ma wep werzeci izrapda jefam rajen repitovu idu haji zitpof go dutas dikboklu gib novfohawe to waanumi. Gudev juer cakralpi efagevjet jaf icuji ihoco toh lezof hazseze vofus kiwut kid. Azulo feiggit vezuwa sov murimno pacurhe evadenfu zu ucfeded co kijcaw jam ropek apipi lac."
  },
  "apiKey": "358ddc740458dcba8268bf40c25622a90d520623152b80c1a389ffc30148ae61",
  "currency": {
    "code": "NGN",
    "name": "Nigeria Naira"
  }
}