{
  "name": "Isaac Norton",
  "age": 41,
  "address": {
    "street": "Bosap Junction",
    "city": "Avotuzku",
    "state": "PA",
    "zip": "72487"
  },
  "contact": {
    "phone": "(730) 573-7658",
    "servicePhone": "800256645"
  },
  "birthday": "1965-04-18T13:27:38.045Z",
  "ip": "175.125.181.59",
  "foo": "bar",
  "profile": {
    "about": "Ocevaj itesi wav huw ebe ocicovali relwofpaf lokmitgak mun fadaak icoco ruv gib te ijevohpa vutuh nafasi. Buznina usasoz wura iphaud cuslu faaju nilmitas besfusbe urozo fi dishis hohluvbu bahtahnis budmas juosu nabwauv. Baha gu viv ojcomjum nofem az hadcov jetfoj bal utoummi sa riwe. Fi rivbij ram wigmin zepu bul uh nanajjif pica befisa evunojecu ilisuima fa rowakse. Dod iwe jifpuf necaz dacel bo cuka hivdik segtommar ageimno nencusu ol bosibpes tas. Suwo cud rapadna si fimkud sidsu vor nasnu zob zossi zubinu undu kabuweane.",
    "bio": "Oka neh ontepe cokapo vel urasuw ekbirsan reweucu ki lunfev doikle figir efaib wutasac gudiz bimvomkiz celdiudi. Jovuku uwiza zuiza usinu sezuwed wi ut vuimian lugsihza mum ewid duku abe denitril. Gob got be gis cisid gibcuncob ducu je magwoju him tivhu mojne kobaj zu vi oljeb tuvo valsinov. Bo gogilho sebi zuzewa ezuhat cuezwor upi jintagcal hidre pesru le diga vepuco fecomi erjummaw melipta ivhujko. Gisajedud ur uroc reiv iradij ri elifezco zohwuwre nulephi zuj velume cek siwpen naigki kelwaude miju eso. Pobto wauce lekouw iz woigo ciz fouc be taitalu fe fivion vut ijjap measmem feneje."
  },
  "apiKey": "5306737ab852a1102f5702adfabfb90ccd1b5ccd2d7de098ba64d24e2913f494",
  "currency": {
    "code": "QAR",
    "name": "Qatar Riyal"
  }
}