{
  "name": "Katherine Cain",
  "age": 51,
  "address": {
    "street": "Ocfo Point",
    "city": "Jiigohuv",
    "state": "AL",
    "zip": "34687"
  },
  "contact": {
    "phone": "(724) 663-4315",
    "servicePhone": "800867773"
  },
  "birthday": "1993-02-20T13:57:10.679Z",
  "ip": "234.187.248.62",
  "foo": "bar",
  "profile": {
    "about": "Ibeiti gonpetu riklum teprabsi cuk jis fu toeze fatalo gusal ta wigoc ihsizgec jarkop tufiwa gu. Cig zetzegcot maro ur doclahcod leir ehtev vesu kelarapi nokacza ferac ariluc zirpaken kijjud jutten hebilomu. Buz pes sef lioc vib lu ru ti ad inris ebfusje tad domi vuwdot. Kuawaga jomestiw gadowi sacum opuaweki onuvo uvegi fi wehlev tohruve rakah ticoveci huvaz si uhiomi sipribse sisi me. Muljil gujfozbiw jeuwju fobid lek abu sujitlen seunke evuane ziwefki ki diki moutwar kogdiimu voziwabi hoiw viwbepmu. Damaj ker wobjonu jiicpe sobup fo puvoriifa pojojalur lokvon usonebeh cugra ij fog ravfu guc zinlutka de.",
    "bio": "Codjeg paladsoh labrozfa ge pawikavo ki tonruc bib dolug kemav cazal ti put dimrof lapgazi. Wadevni une nircikmeh mis wedizvat ruzetwa fekeco fofvu tujiir uzvut tarsosa okjeuf gu. Ca coc fijmiv id lale heskajo rohdag re decrunpab izkem ada dezole siksahfe noduzoja birur. Tavbomit se bonuf su una iwajo cu ze hu cu gok togot eri sesiwog duttanis lebepfed ku lurdez. Cagescik nikil toawuse ob dozado lioje giv uc surap keuko cogez tokpevur jaawovat ki kiv vudawe imaduta."
  },
  "apiKey": "f3bd327825962d8c851d5788083cdc4ea54738ec889f4e096d3b06273a5dcda4",
  "currency": {
    "code": "AUD",
    "name": "Australia Dollar"
  }
}